ot_xchem/__init__.py
ot_xchem/tests/__init__.py
ot_xchem/tests/test_utils/__init__.py
ot_xchem/tests/test_utils/test_parser.py
ot_xchem/tests/test_utils/test_protocols.py
ot_xchem/tests/test_utils/test_reactions.py
ot_xchem/tests/test_utils/test_utils.py
ot_xchem/utils/__init__.py
ot_xchem/utils/parser.py
ot_xchem/utils/protocols.py
ot_xchem/utils/reactions.py
ot_xchem/utils/utils.py
scripts/__init__.py
scripts/parser.py
tests/test_utils/__init__.py
tests/test_utils/test_parser.py
tests/test_utils/test_protocols.py
tests/test_utils/test_reactions.py
tests/test_utils/test_utils.py
utils/__init__.py
utils/parser.py
utils/protocols.py
utils/reactions.py
utils/utils.py
xchem_ot-0.0.6.dist-info/METADATA
xchem_ot-0.0.6.dist-info/RECORD
xchem_ot-0.0.6.dist-info/WHEEL
xchem_ot-0.0.6.dist-info/entry_points.txt
xchem_ot-0.0.6.dist-info/top_level.txt
